spalloc-1!7.4.0.dist-info/licenses/LICENSE
spalloc-1!7.4.0.dist-info/licenses/LICENSE_POLICY.md
spalloc_client/__init__.py
spalloc_client/_keepalive_process.py
spalloc_client/_utils.py
spalloc_client/_version.py
spalloc_client/job.py
spalloc_client/protocol_client.py
spalloc_client/py.typed
spalloc_client/spalloc_config.py
spalloc_client/states.py
spalloc_client/term.py
spalloc_client/scripts/__init__.py
spalloc_client/scripts/alloc.py
spalloc_client/scripts/job.py
spalloc_client/scripts/machine.py
spalloc_client/scripts/ps.py
spalloc_client/scripts/support.py
spalloc_client/scripts/where_is.py
spalloc-1!7.4.0.dist-info/METADATA
spalloc-1!7.4.0.dist-info/WHEEL
spalloc-1!7.4.0.dist-info/entry_points.txt
spalloc-1!7.4.0.dist-info/top_level.txt
spalloc-1!7.4.0.dist-info/zip-safe
spalloc-1!7.4.0.dist-info/RECORD
