Metadata-Version: 2.4
Name: spalloc
Version: 1!7.4.0
Summary: A client for the spalloc_server SpiNNaker machine partitioning and allocation system.
Home-page: https://github.com/SpiNNakerManchester/spalloc
Maintainer: SpiNNakerTeam
Maintainer-email: spinnakerusers@googlegroups.com
License: Apache-2.0
Keywords: spinnaker,allocation,packing management,supercomputer
Classifier: Development Status :: 5 - Production/Stable
Classifier: Intended Audience :: Developers
Classifier: Intended Audience :: Science/Research
Classifier: Natural Language :: English
Classifier: Operating System :: POSIX :: Linux
Classifier: Operating System :: Microsoft :: Windows
Classifier: Operating System :: MacOS
Classifier: Programming Language :: Python :: 3
Classifier: Programming Language :: Python :: 3.8
Classifier: Programming Language :: Python :: 3.9
Classifier: Programming Language :: Python :: 3.10
Classifier: Programming Language :: Python :: 3.11
Classifier: Programming Language :: Python :: 3.12
Classifier: Programming Language :: Python :: 3.13
Requires-Python: <4,>=3.8
License-File: LICENSE
License-File: LICENSE_POLICY.md
Requires-Dist: jsonschema
Requires-Dist: SpiNNUtilities==1!7.4.0
Provides-Extra: test
Requires-Dist: pytest-cov; extra == "test"
Requires-Dist: mock; extra == "test"
Requires-Dist: types-appdirs; extra == "test"
Dynamic: license-file
